pyrarecomb/__init__.py
pyrarecomb/compare_enrichment.py
pyrarecomb/compare_enrichment_depletion.py
pyrarecomb/compare_enrichment_modifiers.py
pyrarecomb/utils/__init__.py
pyrarecomb/utils/helpers.py
pyrarecomb/utils/run_apriori_freqitems.py
pyrarecomb-0.1.4.dist-info/LICENSE
pyrarecomb-0.1.4.dist-info/METADATA
pyrarecomb-0.1.4.dist-info/WHEEL
pyrarecomb-0.1.4.dist-info/top_level.txt
pyrarecomb-0.1.4.dist-info/RECORD
