Metadata-Version: 2.1
Name: pyrarecomb
Version: 0.1.4
Summary: A python tool to identify oligogenic combinations of genes with rare variants
Home-page: https://github.com/deeprob/pyrarecomb
Author: Deepro Banerjee
Author-email: deepro.2.4@gmail.com
Classifier: Programming Language :: Python :: 3
Classifier: License :: OSI Approved :: MIT License
Classifier: Operating System :: OS Independent
Requires-Python: >=3.0
License-File: LICENSE
Requires-Dist: mlxtend
Requires-Dist: pandas
Requires-Dist: statsmodels
